vgxinstance/__init__.py
vgxinstance/vgxinstance.py
vgxadmin/vgxadmin.py
vgxadmin/__init__.py
pyvgx-3.6.0.dist-info/RECORD
pyvgx-3.6.0.dist-info/WHEEL
pyvgx-3.6.0.dist-info/entry_points.txt
pyvgx-3.6.0.dist-info/top_level.txt
pyvgx-3.6.0.dist-info/METADATA
pyvgx-3.6.0.dist-info/licenses/LICENSE
pyvgx-3.6.0.dist-info/licenses/NOTICE
pyvgx_scripts/vgxdemoservice
pyvgx_scripts/vgxadmin.py
pyvgx_scripts/vgxdemoservice.py
pyvgx_scripts/__init__.py
pyvgx_scripts/vgxinstance.py
pyvgx_scripts/vgxdemoplugin.py
pyvgx-3.6.0.data/scripts/vgxdemoservice
pyvgx-3.6.0.data/scripts/vgxdemoservice.py
pyvgx-3.6.0.data/scripts/vgxdemoplugin.py
pyvgx-3.6.0.data/scripts/vgxdemoservice.cmd
pyvgx/libvgx.dylib
pyvgx/__init__.py
pyvgx/libcxlib.a
pyvgx/pyvgx.cpython-310-darwin.so
