Metadata-Version: 2.4
Name: pyvgx
Version: 3.6.0
Summary: PyVGX - Vector Graph Index Python Extensions
Author-email: Stian Lysne <slysne.dev@gmail.com>
Requires-Python: >=3.9
License-File: LICENSE
License-File: NOTICE
Dynamic: license-file
